envtool.py
setup.py
envtool-0.1.0.dist-info/DESCRIPTION.rst
envtool-0.1.0.dist-info/entry_points.txt
envtool-0.1.0.dist-info/METADATA
envtool-0.1.0.dist-info/metadata.json
envtool-0.1.0.dist-info/pbr.json
envtool-0.1.0.dist-info/RECORD
envtool-0.1.0.dist-info/top_level.txt
envtool-0.1.0.dist-info/WHEEL
