Metadata-Version: 2.0
Name: envtool
Version: 0.1.0
Summary: A tool for managing envdirs and env files.
Home-page: https://github.com/judy2k/envtool
Author: Mark Smith
Author-email: mark.smith@practicalpoetry.co.uk
License: BSD
Keywords: environment,envdir,honcho,foreman,env
Platform: UNKNOWN
Classifier: Development Status :: 2 - Pre-Alpha
Classifier: Intended Audience :: Developers
Classifier: License :: OSI Approved :: BSD License
Classifier: Operating System :: Unix
Classifier: Operating System :: POSIX
Classifier: Environment :: Console
Classifier: Programming Language :: Python
Classifier: Programming Language :: Python :: 2.6
Classifier: Programming Language :: Python :: 2.7
Classifier: Programming Language :: Python :: 3
Classifier: Programming Language :: Python :: 3.3
Classifier: Programming Language :: Python :: 3.4
Classifier: Programming Language :: Python :: Implementation :: CPython
Classifier: Topic :: Utilities
Requires-Dist: future (>=0.15.0)
Requires-Dist: click (>=4.0.0)
